src/__init__.py
src/cli.py
git_message-0.1.0.dist-info/METADATA
git_message-0.1.0.dist-info/WHEEL
git_message-0.1.0.dist-info/entry_points.txt
git_message-0.1.0.dist-info/licenses/LICENSE
git_message-0.1.0.dist-info/RECORD
