Metadata-Version: 2.3
Name: git-message
Version: 0.1.0
Summary: Generate commit messages from git diffs using OpenAI models
Author-email: Artem Barger <artem@bargr.net>
License-Expression: MIT
License-File: LICENSE
Requires-Python: >=3.7
Requires-Dist: openai>=1.0.0
